[
	{
		"inputs": [
			{
				"internalType": "string",
				"name": "_name",
				"type": "string"
			},
			{
				"internalType": "string",
				"name": "_party_name",
				"type": "string"
			},
			{
				"internalType": "uint256",
				"name": "_age",
				"type": "uint256"
			},
			{
				"internalType": "string",
				"name": "_region",
				"type": "string"
			}
		],
		"name": "candidateregister",
		"outputs": [],
		"stateMutability": "nonpayable",
		"type": "function"
	},
	{
		"inputs": [
			{
				"internalType": "string",
				"name": "_name",
				"type": "string"
			},
			{
				"internalType": "uint256",
				"name": "_age",
				"type": "uint256"
			},
			{
				"internalType": "string",
				"name": "_contactnumber",
				"type": "string"
			},
			{
				"internalType": "string",
				"name": "_sex",
				"type": "string"
			}
		],
		"name": "userregister",
		"outputs": [],
		"stateMutability": "nonpayable",
		"type": "function"
	},
	{
		"inputs": [
			{
				"internalType": "uint256",
				"name": "_cid",
				"type": "uint256"
			}
		],
		"name": "votecount",
		"outputs": [],
		"stateMutability": "nonpayable",
		"type": "function"
	},
	{
		"inputs": [],
		"name": "voting",
		"outputs": [],
		"stateMutability": "nonpayable",
		"type": "function"
	},
	{
		"inputs": [
			{
				"internalType": "uint256",
				"name": "_cid",
				"type": "uint256"
			}
		],
		"name": "candidatelist",
		"outputs": [
			{
				"components": [
					{
						"internalType": "uint256",
						"name": "cid",
						"type": "uint256"
					},
					{
						"internalType": "string",
						"name": "name",
						"type": "string"
					},
					{
						"internalType": "string",
						"name": "party_name",
						"type": "string"
					},
					{
						"internalType": "uint256",
						"name": "age",
						"type": "uint256"
					},
					{
						"internalType": "string",
						"name": "region",
						"type": "string"
					},
					{
						"internalType": "address",
						"name": "Candidate",
						"type": "address"
					},
					{
						"internalType": "uint256",
						"name": "count",
						"type": "uint256"
					}
				],
				"internalType": "struct Vote.Candidate",
				"name": "",
				"type": "tuple"
			}
		],
		"stateMutability": "view",
		"type": "function"
	},
	{
		"inputs": [],
		"name": "receiveCid",
		"outputs": [
			{
				"internalType": "uint256",
				"name": "",
				"type": "uint256"
			}
		],
		"stateMutability": "view",
		"type": "function"
	},
	{
		"inputs": [],
		"name": "receiveUid",
		"outputs": [
			{
				"internalType": "uint256",
				"name": "",
				"type": "uint256"
			}
		],
		"stateMutability": "view",
		"type": "function"
	}
]